Metadata-Version: 2.1
Name: huracan
Version: 0.9
Summary: Open source, 0-dimensional, object-oriented airbreathing engine modelling package for preliminary analysis and design of airbreathing engines, divulgation and educational purposes.
Home-page: https://github.com/alopezrivera/huracan
Author: Antonio Lopez Rivera
Author-email: antonlopezr99@gmail.com
License: UNKNOWN
Platform: UNKNOWN
Classifier: Programming Language :: Python :: 3
Classifier: License :: OSI Approved :: GNU General Public License v3 (GPLv3)
Classifier: Operating System :: OS Independent
Requires-Python: >=3.8
